kintro_web/__init__.py
kintro_web/app.py
kintro_web-0.0.1rc8.dist-info/METADATA
kintro_web-0.0.1rc8.dist-info/WHEEL
kintro_web-0.0.1rc8.dist-info/top_level.txt
kintro_web-0.0.1rc8.dist-info/RECORD
